{
  "updated_at": "2026-02-05T10:00:06.219085",
  "account": {
    "equity": 97920.7,
    "cash": -66507.87,
    "buying_power": 1758.49,
    "portfolio_value": 97920.7,
    "pnl_today": -2079.300000000003,
    "pnl_today_pct": -2.079300000000006
  },
  "positions": [
    {
      "symbol": "GLL",
      "qty": 1527.0,
      "entry_price": 19.663333,
      "current_price": 19.42,
      "market_value": 29654.34,
      "cost_basis": 30025.909999,
      "unrealized_pnl": -371.569999,
      "unrealized_pnl_pct": -1.237,
      "side": "long",
      "is_inverse": true,
      "hedging": "GLD"
    },
    {
      "symbol": "SH",
      "qty": 1652.0,
      "entry_price": 36.445,
      "current_price": 36.2999,
      "market_value": 59967.4348,
      "cost_basis": 60207.14,
      "unrealized_pnl": -239.7052,
      "unrealized_pnl_pct": -0.398,
      "side": "long",
      "is_inverse": true,
      "hedging": "SPY"
    },
    {
      "symbol": "SQQQ",
      "qty": 1020.0,
      "entry_price": 74.779235,
      "current_price": 73.34,
      "market_value": 74806.8,
      "cost_basis": 76274.82,
      "unrealized_pnl": -1468.02,
      "unrealized_pnl_pct": -1.925,
      "side": "long",
      "is_inverse": true,
      "hedging": "QQQ/NVDA"
    }
  ],
  "recent_trades": [
    {
      "symbol": "SH",
      "side": "buy",
      "qty": 413.0,
      "price": 36.46,
      "filled_at": "2026-02-05T15:14:03.112740+00:00",
      "status": "filled"
    },
    {
      "symbol": "SQQQ",
      "side": "buy",
      "qty": 136.0,
      "price": 74.97,
      "filled_at": "2026-02-05T15:13:02.291240+00:00",
      "status": "filled"
    },
    {
      "symbol": "GLL",
      "side": "buy",
      "qty": 509.0,
      "price": 19.7,
      "filled_at": "2026-02-05T15:13:01.102487+00:00",
      "status": "filled"
    },
    {
      "symbol": "SQQQ",
      "side": "buy",
      "qty": 204.0,
      "price": 74.97,
      "filled_at": "2026-02-05T15:13:01.813614+00:00",
      "status": "filled"
    },
    {
      "symbol": "SH",
      "side": "buy",
      "qty": 413.0,
      "price": 36.46,
      "filled_at": "2026-02-05T15:12:59.345470+00:00",
      "status": "filled"
    },
    {
      "symbol": "SQQQ",
      "side": "buy",
      "qty": 136.0,
      "price": 74.79,
      "filled_at": "2026-02-05T15:11:58.130183+00:00",
      "status": "filled"
    },
    {
      "symbol": "GLL",
      "side": "buy",
      "qty": 509.0,
      "price": 19.67,
      "filled_at": "2026-02-05T15:11:58.498103+00:00",
      "status": "filled"
    },
    {
      "symbol": "SQQQ",
      "side": "buy",
      "qty": 204.0,
      "price": 74.79,
      "filled_at": "2026-02-05T15:11:57.785720+00:00",
      "status": "filled"
    },
    {
      "symbol": "SH",
      "side": "buy",
      "qty": 413.0,
      "price": 36.44,
      "filled_at": "2026-02-05T15:11:56.630340+00:00",
      "status": "filled"
    },
    {
      "symbol": "SQQQ",
      "side": "buy",
      "qty": 136.0,
      "price": 74.603824,
      "filled_at": "2026-02-05T15:10:56.111954+00:00",
      "status": "filled"
    },
    {
      "symbol": "GLL",
      "side": "buy",
      "qty": 509.0,
      "price": 19.62,
      "filled_at": "2026-02-05T15:10:54.320719+00:00",
      "status": "filled"
    },
    {
      "symbol": "SQQQ",
      "side": "buy",
      "qty": 204.0,
      "price": 74.560294,
      "filled_at": "2026-02-05T15:10:54.356691+00:00",
      "status": "filled"
    },
    {
      "symbol": "SH",
      "side": "buy",
      "qty": 413.0,
      "price": 36.42,
      "filled_at": "2026-02-05T15:10:53.161852+00:00",
      "status": "filled"
    }
  ],
  "strategy": "RegimeHold + Inverse ETFs",
  "regime_status": {},
  "summary": {
    "total_positions": 3,
    "total_invested": 164428.5748,
    "total_unrealized_pnl": -2079.295199,
    "total_unrealized_pnl_pct": -1.2645583053487612,
    "cash_remaining": -66507.87
  }
}